snappi_trex/__init__.py
snappi_trex/capture.py
snappi_trex/exceptions.py
snappi_trex/info.py
snappi_trex/link.py
snappi_trex/metrics.py
snappi_trex/setconfig.py
snappi_trex/snappi_api.py
snappi_trex/util.py
snappi_trex/validation.py
snappi_trex/valueoptions.py
snappi_trex-0.1.6.dist-info/LICENSE
snappi_trex-0.1.6.dist-info/METADATA
snappi_trex-0.1.6.dist-info/WHEEL
snappi_trex-0.1.6.dist-info/top_level.txt
snappi_trex-0.1.6.dist-info/RECORD
