Metadata-Version: 2.1
Name: snappi-trex
Version: 0.1.6
Summary: The TRex Open Traffic Generator Python Package
Home-page: https://github.com/open-traffic-generator
Author: fredpower44
Author-email: frederick.zhang@keysight.com
License: MIT
Keywords: TRex testing open traffic generator automation
Platform: UNKNOWN
Classifier: Development Status :: 3 - Alpha
Classifier: Intended Audience :: Developers
Classifier: Topic :: Software Development :: Testing :: Traffic Generation
Classifier: License :: OSI Approved :: MIT License
Classifier: Programming Language :: Python :: 3
Requires-Python: >=3, <4
License-File: LICENSE
Provides-Extra: dev
Requires-Dist: snappi (==0.3.20) ; extra == 'dev'
Requires-Dist: pytest ; extra == 'dev'
Requires-Dist: flake8 (==3.8.4) ; extra == 'dev'
Requires-Dist: dpkt (==1.9.4) ; extra == 'dev'
